constitute_mcp/__init__.py
constitute_mcp/fastmcp_server.py
constitute_mcp/scraper.py
constitute_mcp/server.py
constitute_mcp-0.1.26.dist-info/licenses/LICENSE
constitute_mcp-0.1.26.dist-info/METADATA
constitute_mcp-0.1.26.dist-info/WHEEL
constitute_mcp-0.1.26.dist-info/entry_points.txt
constitute_mcp-0.1.26.dist-info/top_level.txt
constitute_mcp-0.1.26.dist-info/RECORD
